scFlash/__init__.py
scFlash/Datasets/GeneExpression.py
scFlash/Datasets/__init__.py
scFlash/Denoising/DCA.py
scFlash/Denoising/__init__.py
scFlash/Denoising/deepimpute.py
scFlash/Denoising/scScope.py
scFlash/Dim_reduction/PCA.py
scFlash/Dim_reduction/TSNE.py
scFlash/Dim_reduction/VAE.py
scFlash/Dim_reduction/__init__.py
scFlash/utils/__init__.py
scFlash/utils/losses.py
scFlash/utils/modules.py
scFlash/utils/preprocessing.py
scFlash/utils/utils.py
scFlash-1.0.1.dist-info/LICENSE
scFlash-1.0.1.dist-info/METADATA
scFlash-1.0.1.dist-info/WHEEL
scFlash-1.0.1.dist-info/top_level.txt
scFlash-1.0.1.dist-info/RECORD
