Metadata-Version: 2.1
Name: scFlash
Version: 1.0.1
Summary: One stop solution for Single Cell analysis
Home-page: https://github.com/bayeslabs/scFlash
Author: Sarath Kolli, Anudeep Kota, Aysha Saniya, Kushan Raj, Meenakshi Pillai, Niranjan Jain, Rujutha Shinde, Shraddha Bharadwaj
License: MIT
Keywords: SCA,SC-RNA SEQ
Platform: UNKNOWN
Classifier: License :: OSI Approved :: MIT License
Classifier: Programming Language :: Python :: 3
Classifier: Programming Language :: Python :: 3.7
Classifier: Development Status :: 1 - Planning
Classifier: Intended Audience :: Developers
Classifier: Operating System :: Unix
Classifier: Operating System :: MacOS :: MacOS X
Classifier: Operating System :: Microsoft :: Windows
Requires-Dist: bs4
Requires-Dist: requests
